Workbook
Name m_性別: '_マスタ（非表示）'!$A$2:$A$3
Name m_雇用形態: '_マスタ（非表示）'!$B$2:$B$7
Name m_賃金形態: '_マスタ（非表示）'!$C$2:$C$6
Name m_更新見込み: '_マスタ（非表示）'!$D$2:$D$4
Name m_後日提出: '_マスタ（非表示）'!$E$2:$E$2
Name m_番号提出状態: '_マスタ（非表示）'!$F$2:$F$3
Name m_ありなし: '_マスタ（非表示）'!$G$2:$G$3
Name m_なしあり: '_マスタ（非表示）'!$H$2:$H$3
Name m_学生区分: '_マスタ（非表示）'!$I$2:$I$4
Name m_前職雇保: '_マスタ（非表示）'!$J$2:$J$4
Name m_健保種類: '_マスタ（非表示）'!$K$2:$K$3
Name m_任意申出: '_マスタ（非表示）'!$L$2:$L$3
Name m_資格確認書: '_マスタ（非表示）'!$M$2:$M$4
Name m_続柄: '_マスタ（非表示）'!$N$2:$N$8
Name m_同居別居: '_マスタ（非表示）'!$O$2:$O$3
Name m_第3号: '_マスタ（非表示）'!$P$2:$P$3
Name m_国籍: '_マスタ（非表示）'!$Q$2:$Q$3
Name m_都道府県: '_マスタ（非表示）'!$R$2:$R$48
Name 厚年被保険者数: '⓪ 事業所設定'!$C$9
Name 企業規模区分: '⓪ 事業所設定'!$C$10
Name 短時間適用: '⓪ 事業所設定'!$C$12
Name 正社員週所定: '⓪ 事業所設定'!$C$13
Name 正社員月所定: '⓪ 事業所設定'!$C$14
Name 判定基準日: '⓪ 事業所設定'!$C$17
Name m_職種: '_マスタ（非表示）'!$S$2:$S$13
Name m_現物給与種類: '_マスタ（非表示）'!$T$2:$T$6

Sheet はじめにお読みください（記入要領）
B1: 入社時 従業員情報 受領フォーム
B2: はじめにお読みください（記入要領）
B4: この書類について
B5: 事務所名 | C5: みなの社会保険労務士事務所
B6: お問い合わせ | C6: 076-460-2562 / contact@minano-sr.com
B7: バージョン | C7: 1.0（更新日 2026-09-11）
B9: 目的
C10: 健康保険・厚生年金保険と雇用保険の資格取得手続きに必要な情報をご記入いただくフォームです。
B12: 入力の流れ（所要時間の目安：1名あたり 5〜10分）
B13: STEP 1 | C13: シート『⓪ 事業所設定』を最初に一度だけ設定します（会社全体の情報。2回目以降は不要）。
B14: STEP 2 | C14: シート『① 従業員情報（本人）』に、入社者を1行＝1名で入力します。複数名まとめて入力できます。
B15: STEP 3 | C15: 被扶養者がいる方は、シート『② 被扶養者情報』にも入力します（本人の『フォーム内No.』で紐付け）。
B16: ヒント | C16: 上部の『進捗ブロック』で、未入力の残件数・完了率が自動表示されます。100%を目指してご記入ください。
B18: 色の凡例
B19: 必須項目 | C19: ヘッダーが薄い黄色。必ず入力してください。
B20: 任意項目 | C20: ヘッダーが薄い灰色。該当する場合に入力してください。【条件必須】と書かれた欄は、その条件に当てはまる方は必ず入力してください。
B21: 自動計算 | C21: 灰色。自動で計算・判定されます（上書きしないでください）。
B22: 未入力の警告 | C22: 必須なのに空欄のセルが薄い赤で点灯します。入力すると消えます。
B23: 形式の警告 | C23: 桁数・全角カナ・姓名間スペース・日付の形式が想定と違うと薄い橙で点灯します。
B24: 対象外（記入不要） | C24: 暗い灰＋斜線。雇用期間の定め＝なし のときの契約満了日など、記入が不要な欄です。
B25: 問題なし | C25: 薄い緑。年齢注記などで注意事項が無く、問題ないことを示します。
B26: 判定：加入 | C26: 加入対象の目安。薄い緑。
B27: 判定：対象外 | C27: 加入対象外の目安。薄い灰色。
B29: 加入判定について（重要）
C30: 『健保・厚年 加入判定』『雇用保険 加入判定』の列は、入力された勤務条件と⓪事業所設定から自動で表示される目安です。実際の加入要否の最終判断は社会保険労務士が行います。判定結果に疑問がある場合や、契約内容が変則的な場合は、そのまま当事務所へご連絡ください。
B32: マイナンバー等 機微情報の取扱い
B33: 入力時 | C33: マイナンバー（12桁）は半角数字・ハイフン無しで入力できます。会社所定の安全な経路で別提出する場合は、番号を入力せず『別経路提出』を選んでください。入社時点で未回収の場合は『後日提出』を選択します。
B34: 返送方法 | C34: 受任メールのリンクから案件ページを開き、記入したこのファイルをそのままお送りください。ZIPにする必要はありません。この経路は暗号化されており、メール添付より安全です。メールに直接添付して送るのは避けてください（マイナンバー等の特定個人情報を含みます）。
B35: 社内保管 | C35: 記入途中のファイルは関係者以外がアクセスできない場所に保管し、提出後は社内ルールに従って適切に削除・保管してください。
B37: 入社時点で情報が揃わないとき（必須項目の書き方）
B38: 本人にご確認いただく欄 | C38: 本人にご確認いただく欄は、当事務所の書式『入社時 本人情報記入シート』（https://minano-sr.com/shoshiki/D-52.html）を印刷してご本人に記入いただくと、そのままこのフォームに転記できます。
B39: 基本の考え方 | C39: 入社時点でどうしても分からない欄は、空欄のまま備考に『○○は後日提出』とご記入ください。分かり次第ご連絡いただければ当方で補います。下記は特に間違えやすい番号類の扱いです。
B40: 基礎年金番号 | C40: マイナンバーをご記入いただければ、基礎年金番号は省略できます（資格取得届はマイナンバーで提出できます）。マイナンバーを別経路提出にする、または番号が不明なときは、セルのドロップダウンから『後日提出』を選んでください（未入力扱いになりません）。
B41: 雇用保険被保険者番号 | C41: 初めて就職する方・前職が無い方は空欄で構いません（新しく番号を取得します）。前職はあるが番号が不明なときは『後日提出』を選択してください。
B42: 2か月超／31日以上 見込み | C42: この2列は自動表示です（入力不要）。雇用期間の定め・契約満了日・更新の見込みを入れると自動で判定されます。
B43: 困ったときは
C44: 入力方法が分からない・選択肢に当てはまるものが無い・判定結果に疑問がある等、どんなことでも上記『お問い合わせ』先（076-460-2562 / contact@minano-sr.com）までお気軽にご連絡ください。

Sheet 提出チェック・添付・返送
B1: 入社時 従業員情報 提出チェック・添付・返送
B2: このシートは貴社（ご担当者さま）が、入力 → 提出前の確認 → 当事務所への返送まで迷わず進めるための案内です。本体シートをご記入のうえ、最後にここをご確認ください。
B4: ① 提出前チェック
B5: 貴社名 | D5: 貴社名をご記入ください。
B6: ご入力担当者名 | D6: このフォームをご記入された方のお名前。
B7: ご担当者 連絡先 | D7: 電話番号またはメールアドレス。確認時の連絡用。
B8: 記入日 | D8: ご記入（最終確認）日。
B9: 対象者数（自動） | C9: ='① 従業員情報（本人）'!B4 | D9: 本体シートに入力された件数を自動表示します。
B10: 必須の未入力 残（自動） | C10: ='① 従業員情報（本人）'!F4 | D10: 未入力の必須項目の残数。0件になるまでご記入ください（本体の薄赤・行ステータス参照）。
B11: 完了率（自動） | C11: ='① 従業員情報（本人）'!L4 | D11: 必須項目の充足率。
B12: 提出可否（自動） | C12: =IF('① 従業員情報（本人）'!B4=0,"未入力（対象者なし）",IF(AND('① 従業員情報（本人）'!F4=0,'① 従業員情報（本人）'!D4<>'① 従業員情報（本人）'!B4),"確認が必要：式の入っていない行があります（行を挿入せず9〜58行にご記入ください）",IF(COUNTBLANK('⓪ 事業所設定'!$C$6)+COUNTBLANK('⓪ 事業所設定'!$C$8)+COUNTBLANK('⓪ 事業所設定'!$C$9)+COUNTBLANK('⓪ 事業所設定'!$C$11)+COUNTBLANK('⓪ 事業所設定'!$C$13)+COUNTBLANK('⓪ 事業所設定'!$C$14)+COUNTBLANK('⓪ 事業所設定'!$C$17)+COUNTBLANK('⓪ 事業所設定'!$C$19)+COUNTBLANK('⓪ 事業所設定'!$C$20)+COUNTBLANK('⓪ 事業所設定'!$C$21)>0,"未入力あり：⓪事業所設定をご記入ください",IF('① 従業員情報（本人）'!F4>0,"未入力あり：本体シートの薄赤セル・行ステータスをご確認ください",IF('② 被扶養者情報'!E4>0,"未入力あり：②被扶養者情報をご確認ください",IF(ISNUMBER(SEARCH("未入力",$C$13)),"未入力あり：被扶養者ありの方の②をご記入ください","提出可（必須の未入力なし）")))))) | D12: ⓪事業所設定・①本体・②被扶養者のすべてに必須の未入力が無ければ『提出可』。
B13: 被扶養者の突合（自動） | C13: =IF('① 従業員情報（本人）'!$B$4=0,"—",IF(COUNTIFS('① 従業員情報（本人）'!$B$9:$B$58,"<>",'① 従業員情報（本人）'!$AQ$9:$AQ$58,"あり")=SUMPRODUCT(('② 被扶養者情報'!$A$8:$A$67<>"")/COUNTIF('② 被扶養者情報'!$A$8:$A$67,'② 被扶養者情報'!$A$8:$A$67&"")),"✓ 一致（被扶養者ありの方 "&COUNTIFS('① 従業員情報（本人）'!$B$9:$B$58,"<>",'① 従業員情報（本人）'!$AQ$9:$AQ$58,"あり")&" 名／②の対象者 "&SUMPRODUCT(('② 被扶養者情報'!$A$8:$A$67<>"")/COUNTIF('② 被扶養者情報'!$A$8:$A$67,'② 被扶養者情報'!$A$8:$A$67&""))&" 名）","被扶養者ありの方の②が未入力です（①であり "&COUNTIFS('① 従業員情報（本人）'!$B$9:$B$58,"<>",'① 従業員情報（本人）'!$AQ$9:$AQ$58,"あり")&" 名／②の対象者 "&SUMPRODUCT(('② 被扶養者情報'!$A$8:$A$67<>"")/COUNTIF('② 被扶養者情報'!$A$8:$A$67,'② 被扶養者情報'!$A$8:$A$67&""))&" 名）")) | D13: ①で『被扶養者の有無＝あり』の人数と、②に入力された対象者の人数を突き合わせます。
B14: 事務所への連絡事項 | D14: 不明点・特記事項があればご記入ください（任意）。
B15: ② 一緒に送っていただく書類
B16: 書類の一覧と、いま何が届いているかは案件ページが正です。このシートには書類の状態を書かないでください（二重管理になります）。 案件ページは受任メールのリンクから開けます。届いた書類はその場で受領済みに変わります。
B17: この手続きで必要になるもの | D17: （案件ページの一覧が正です）
B18: マイナンバー確認資料 | D18: 個人番号カード・通知カード・マイナンバー記載の住民票など。フォームへ直接入力しない場合は安全な別経路で提出。
B19: 基礎年金番号がわかる資料 | D19: 年金手帳・基礎年金番号通知書など。マイナンバーで提出する場合は省略可（不明は『後日提出』）。
B20: 雇用保険被保険者番号がわかる資料 | D20: 前職の離職票・雇用保険被保険者証。新卒・前職なしは新規取得（『該当なし』）。
B21: 扶養に入れる家族の確認資料（被扶養者がいる場合） | D21: 続柄・収入のわかる資料。被扶養者シート②もご記入ください。
B22: 在留カード（外国籍の場合） | D22: 在留資格・在留期間の確認に使用。
B23: 給与振込口座の資料（口座情報が必要な運用の場合） | D23: 貴社の運用で必要な場合のみ。
B25: ③ 当事務所への返送について
B26: 【ご返送方法】 記入したこのファイルを、案件ページからそのままお送りください。ZIPにする必要はありません。ファイル名も変えなくて構いません。 案件ページ＝受任メールのリンクから開けます。この経路は暗号化されており、メール添付より安全です。 メールに直接添付して送るのは避けてください（マイナンバー等の特定個人情報を含みます）。
B32: ④ 入力の補足（情報が揃わないとき）
B33: ・『不明』『後日提出』を選べる欄は、空欄のままにせず状態を残してください。後で当事務所が確認・督促できます。 ・該当しない欄は『該当なし』を選ぶか空欄で構いません（条件次第で対象外＝斜線になる欄もあります）。 ・色の意味：薄黄＝必須／薄青＝当事務所が補完／薄赤＝必須の未入力／薄橙＝形式の確認／斜線＝記入不要。

Sheet ⓪ 事業所設定
B1: ⓪ 事業所設定
B2: 最初に一度だけ設定してください。①従業員情報シートの加入判定がこの設定を参照します。
B3: 【企業規模要件】特定適用事業所の人数要件は、2027年10月以降に 51人→（順次）と段階的に縮小される予定です（2024/10時点は51人以上）。本フォームの企業規模区分は、下の被保険者数の設定値で判定します。
B4: 【所定内賃金 8.8万円要件】2026年10月に撤廃が予定されています。下の『判定基準日』が 2026/10/1 以降のとき、本要件は自動的に無効化されます。
B6: 【必】 会社名 | D6: 適用事業所の名称。
B7: 【任】 法人番号（13桁） | D7: 国税庁の13桁の法人番号。
B8: 【必】 健康保険の種類 | D8: 協会けんぽ／健康保険組合 のいずれか。
B9: 【必】 厚生年金保険の被保険者数 | D9: 同一法人番号の全適用事業所の合算。短時間労働者本人・70歳以上で健保のみの者は含めない。
B10: 【自動】 〔自動〕企業規模区分 | C10: =IF(C9="","",IF(C9>=51,"特定適用事業所（51人以上）","50人以下")) | D10: 被保険者数 51人以上で『特定適用事業所』。自動表示。
B11: 【必】 任意特定適用事業所の申出 | D11: 50人以下でも労使合意で短時間労働者に適用する場合は『あり』。
B12: 【自動】 〔自動〕短時間労働者への適用 | C12: =IF(C9="","",IF(OR(C9>=51,C11="あり"),"適用あり","適用なし")) | D12: 被保険者数51人以上、または任意申出『あり』で『適用あり』。
B13: 【必】 正社員の1週間の所定労働時間(h) | D13: 4分の3基準の分母。通常の労働者（正社員）の契約上の週所定。
B14: 【必】 正社員の1か月の所定労働日数(日) | D14: 4分の3基準の分母。通常の労働者（正社員）の月所定日数。
B15: 【自動】 〔自動〕4分の3しきい値（週・h） | C15: =IF(C13="","",C13*0.75) | D15: 正社員週所定 × 0.75。これ以上で4分の3基準（週）を満たす。
B16: 【自動】 〔自動〕4分の3しきい値（月・日） | C16: =IF(C14="","",C14*0.75) | D16: 正社員月所定日数 × 0.75。これ以上で4分の3基準（月）を満たす。
B17: 【必】 判定基準日 | C17: =TODAY() | D17: 賃金要件（8.8万円）の施行日分岐に使用。既定は本日。手入力で上書き可。
B18: 【任】 〔参考〕事業所所在地の最低賃金(円) | D18: 任意。参考情報として保持。
B19: 【必】 健康保険・厚生年金の事業所整理記号 | D19: 毎月20日ごろ年金事務所から届く「保険料納入告知額・領収済額通知書」に載っています。口座振替の会社は別名の紙で届きます。例）12-アイウ 2回目以降のご注文で、前回お知らせいただいていれば「前回と同じ」とご記入ください。
B20: 【必】 同 事業所番号 | D20: 同じ紙の、整理記号の隣にある番号です。5桁。 2回目以降のご注文で、前回お知らせいただいていれば「前回と同じ」とご記入ください。
B21: 【必】 雇用保険の事業所番号 | D21: 「雇用保険適用事業所設置届 事業主控」または資格取得等確認通知書に載っています。4桁-6桁-1桁。例）1610-123456-7 2回目以降のご注文で、前回お知らせいただいていれば「前回と同じ」とご記入ください。

Sheet ① 従業員情報（本人）
A1: ① 従業員情報（本人） | K1: ※加入判定は目安です。最終判断は社労士が行います。
B3: 入力対象人数 | D3: 必須充足人数 | F3: 必須未入力 残件数 | I3: 形式エラー件数 | L3: 完了率
B4: =COUNTA(B9:B58) | D4: =COUNTIF(AT9:AT58,0) | F4: =SUM(AT9:AT58) | I4: =SUM(AU9:AU58) | L4: =IF(B4=0,0,D4/B4)
B5: =IF(B4=0,"（まだ入力がありません。水色の記入例の下の行からご記入ください）",IF(AND(F4=0,D4<>B4),"⚠ 式の入っていない行があります：行を挿入せず 9〜58 行にご記入ください",IF(F4=0,"✓ 必須の未入力はありません","⚠ 必須の未入力が "&F4&" 件あります：本体の赤いセルをご確認ください")))
A6: A基本情報 | G6: B雇用・勤務条件 | Q6: C賃金 | X6: D加入判定（自動） | AA6: E番号・本人確認 | AG6: F住所・連絡先 | AL6: G国籍 | AP6: Hその他 | AV6: I追加項目（職種・賃金要件・二以上勤務）
A7: フォーム内No. 【自動】 | B7: 氏名（漢字） 【必】 | C7: 氏名（フリガナ） 【必】 | D7: 性別 【必】 | E7: 生年月日 【必】 | F7: 年齢 【自動】 | G7: 入社日／資格取得日 【必】 | H7: 雇用形態 【必】 | I7: 雇用期間の定め 【必】 | J7: 契約満了日 【任】 | K7: 契約更新の見込み 【任】 | L7: 週の所定労働時間(h) 【必】 | M7: 月の所定労働日数(日) 【必】 | N7: 学生区分 【必】 | O7: 2か月超 雇用見込み 【自動】 | P7: 31日以上 雇用見込み 【自動】 | Q7: 賃金形態 【必】 | R7: 時給・日給の単価(円) 【任】 | S7: 基本給(月額・円) 【必】 | T7: 固定手当(月額・円) 【任】 | U7: 通勤手当(1か月相当・円) 【任】 | V7: 現物給与(月額相当・円) 【任】 | W7: 報酬月額 合計 【自動】 | X7: 健保・厚年 加入判定 【自動】 | Y7: 年齢注記 【自動】 | Z7: 雇用保険 加入判定 【自動】 | AA7: マイナンバー(12桁) 【必】 | AB7: 基礎年金番号(10桁) 【必】 | AC7: 前職での雇用保険加入 【必】 | AD7: 雇用保険被保険者番号(11桁) 【必】 | AE7: 前職の事業所名(番号不明時) 【任】 | AF7: 前職の退職年月日(番号不明時) 【任】 | AG7: 郵便番号 【必】 | AH7: 都道府県 【必】 | AI7: 市区町村以下 【必】 | AJ7: 建物名・部屋番号 【任】 | AK7: 電話番号 【任】 | AL7: 国籍 【必】 | AM7: 在留資格 【条件必須】外国籍のとき | AN7: 在留期間満了日 【条件必須】外国籍のとき | AO7: ローマ字氏名 【条件必須】外国籍のとき | AP7: 資格確認書 発行要否 【必】 | AQ7: 被扶養者の有無 【必】 | AR7: 備考 【任】 | AV7: 職種（雇用保険） 【必】 | AW7: うち家族手当・精皆勤手当 (月額・円) 【任】 | AX7: 他社でも社会保険に加入 【任】 | AY7: 現物給与の種類 【条件必須】現物給与があるとき
A8: 例 | B8: 山田 太郎 | C8: ヤマダ タロウ | D8: 男 | E8: 32964 | F8: =IF(OR($E8="",$E8>80000),"",DATEDIF($E8,IF(OR($G8="",$G8>80000),TODAY(),$G8),"Y")) | G8: 46204 | H8: 正社員 | I8: なし | L8: 40 | M8: 21 | N8: 学生ではない | O8: =IF($B8="","",IF($I8="なし","あり",IF($I8<>"あり","",IF($K8="更新の可能性あり","あり",IF(OR($J8="",$G8=""),"なし",IF(OR(NOT(ISNUMBER($G8)),NOT(ISNUMBER($J8)),$G8>80000,$J8>80000),"要確認（日付）",IF($J8>IF(DAY(EDATE($G8,2))<DAY($G8),EOMONTH($G8,2),EDATE($G8,2)-1),"あり","なし")))))) | P8: =IF($B8="","",IF($I8="なし","あり",IF($I8="あり",IF(OR($K8="更新の可能性あり",AND($J8<>"",$G8<>"",$J8-$G8+1>=31)),"あり","なし"),""))) | Q8: 月給 | S8: 250000 | T8: 20000 | U8: 12000 | V8: 0 | W8: =IF($B8="","",SUM($S8,$T8,$U8,$V8)) | X8: =IF(OR('⓪ 事業所設定'!$C$9="",'⓪ 事業所設定'!$C$13="",'⓪ 事業所設定'!$C$14="",'⓪ 事業所設定'!$C$17=""),"事業所設定が未入力です",IF($B8="","",IF(AND($L8>='⓪ 事業所設定'!$C$13*0.75,$M8>='⓪ 事業所設定'!$C$14*0.75,$O8="あり"),"加入（一般被保険者）",IF(AND('⓪ 事業所設定'!$C$12="適用あり",$L8>=20,$O8="あり",$N8<>"昼間部の学生",OR('⓪ 事業所設定'!$C$17>=DATE(2026,10,1),($S8+$T8-N($AW8))>=88000)),"加入（短時間労働者）","加入対象外")))) | Y8: =IF($B8="","",TRIM(IF(AND($F8<>"",$F8>=70,ISNUMBER(SEARCH("加入（",$X8))),"厚年対象外（70歳以上被用者該当届） ","")&IF(AND($F8<>"",$F8>=75),"健保対象外（後期高齢者医療） ","")&IF(AND($F8<>"",$F8>=65,$Z8="加入"),"雇保：高年齢被保険者 ",""))) | Z8: =IF($B8="","",IF($H8="役員","対象外（兼務役員なら要相談）",IF(AND($L8>=20,$P8="あり",$N8<>"昼間部の学生"),"加入","加入対象外"))) | AA8: 123456789012 | AC8: なし | AG8: 100-0001 | AH8: 東京都 | AI8: 千代田区千代田1-1 | AJ8: 〇〇マンション101 | AK8: 03-1234-5678 | AL8: 日本 | AP8: 否（登録済み） | AQ8: あり | AR8: ← この行は記入例です。9行目からご記入ください（消しても構いません） | AV8: 事務的職業 | AW8: 0 | AX8: いいえ | AY8: —
A9: =IF($B9="","",ROW()-8) | F9: =IF(OR($E9="",$E9>80000),"",DATEDIF($E9,IF(OR($G9="",$G9>80000),TODAY(),$G9),"Y")) | O9: =IF($B9="","",IF($I9="なし","あり",IF($I9<>"あり","",IF($K9="更新の可能性あり","あり",IF(OR($J9="",$G9=""),"なし",IF(OR(NOT(ISNUMBER($G9)),NOT(ISNUMBER($J9)),$G9>80000,$J9>80000),"要確認（日付）",IF($J9>IF(DAY(EDATE($G9,2))<DAY($G9),EOMONTH($G9,2),EDATE($G9,2)-1),"あり","なし")))))) | P9: =IF($B9="","",IF($I9="なし","あり",IF($I9="あり",IF(OR($K9="更新の可能性あり",AND($J9<>"",$G9<>"",$J9-$G9+1>=31)),"あり","なし"),""))) | W9: =IF($B9="","",SUM($S9,$T9,$U9,$V9)) | X9: =IF(OR('⓪ 事業所設定'!$C$9="",'⓪ 事業所設定'!$C$13="",'⓪ 事業所設定'!$C$14="",'⓪ 事業所設定'!$C$17=""),"事業所設定が未入力です",IF($B9="","",IF(AND($L9>='⓪ 事業所設定'!$C$13*0.75,$M9>='⓪ 事業所設定'!$C$14*0.75,$O9="あり"),"加入（一般被保険者）",IF(AND('⓪ 事業所設定'!$C$12="適用あり",$L9>=20,$O9="あり",$N9<>"昼間部の学生",OR('⓪ 事業所設定'!$C$17>=DATE(2026,10,1),($S9+$T9-N($AW9))>=88000)),"加入（短時間労働者）","加入対象外")))) | Y9: =IF($B9="","",TRIM(IF(AND($F9<>"",$F9>=70,ISNUMBER(SEARCH("加入（",$X9))),"厚年対象外（70歳以上被用者該当届） ","")&IF(AND($F9<>"",$F9>=75),"健保対象外（後期高齢者医療） ","")&IF(AND($F9<>"",$F9>=65,$Z9="加入"),"雇保：高年齢被保険者 ",""))) | Z9: =IF($B9="","",IF($H9="役員","対象外（兼務役員なら要相談）",IF(AND($L9>=20,$P9="あり",$N9<>"昼間部の学生"),"加入","加入対象外"))) | AT9: =IF($B9="","",IF($B9="",1,0)+IF($C9="",1,0)+IF($D9="",1,0)+IF($E9="",1,0)+IF($G9="",1,0)+IF($H9="",1,0)+IF($I9="",1,0)+IF($L9="",1,0)+IF($M9="",1,0)+IF($N9="",1,0)+IF($Q9="",1,0)+IF($S9="",1,0)+IF($AA9="",1,0)+IF($AC9="",1,0)+IF($AG9="",1,0)+IF($AH9="",1,0)+IF($AI9="",1,0)+IF($AL9="",1,0)+IF($AP9="",1,0)+IF($AQ9="",1,0)+IF(AND($I9="あり",$J9=""),1,0)+IF(AND($I9="あり",$K9=""),1,0)+IF(AND($AA9="",$AB9=""),1,0)+IF(AND($AC9="あり",$AD9=""),1,0)+IF(AND($AC9="あり",OR($AD9="",$AD9="後日提出"),$AE9=""),1,0)+IF($AV9="",1,0)+IF(AND($AL9="外国",$AM9=""),1,0)+IF(AND($AL9="外国",$AN9=""),1,0)+IF(AND($AL9="外国",$AO9=""),1,0)) | AU9: =IF($B9="","",IF(AND($AA9<>"",$AA9<>"後日提出",$AA9<>"別経路提出",LEN($AA9)<>12),1,0)+IF(AND($AB9<>"",$AB9<>"後日提出",LEN($AB9)<>10),1,0)+IF(AND($AD9<>"",$AD9<>"後日提出",LEN($AD9)<>11),1,0)+IF(AND($AG9<>"",LEN(SUBSTITUTE($AG9,"-",""))<>7),1,0))
A10: =IF($B10="","",ROW()-8) | F10: =IF(OR($E10="",$E10>80000),"",DATEDIF($E10,IF(OR($G10="",$G10>80000),TODAY(),$G10),"Y")) | O10: =IF($B10="","",IF($I10="なし","あり",IF($I10<>"あり","",IF($K10="更新の可能性あり","あり",IF(OR($J10="",$G10=""),"なし",IF(OR(NOT(ISNUMBER($G10)),NOT(ISNUMBER($J10)),$G10>80000,$J10>80000),"要確認（日付）",IF($J10>IF(DAY(EDATE($G10,2))<DAY($G10),EOMONTH($G10,2),EDATE($G10,2)-1),"あり","なし")))))) | P10: =IF($B10="","",IF($I10="なし","あり",IF($I10="あり",IF(OR($K10="更新の可能性あり",AND($J10<>"",$G10<>"",$J10-$G10+1>=31)),"あり","なし"),""))) | W10: =IF($B10="","",SUM($S10,$T10,$U10,$V10)) | X10: =IF(OR('⓪ 事業所設定'!$C$9="",'⓪ 事業所設定'!$C$13="",'⓪ 事業所設定'!$C$14="",'⓪ 事業所設定'!$C$17=""),"事業所設定が未入力です",IF($B10="","",IF(AND($L10>='⓪ 事業所設定'!$C$13*0.75,$M10>='⓪ 事業所設定'!$C$14*0.75,$O10="あり"),"加入（一般被保険者）",IF(AND('⓪ 事業所設定'!$C$12="適用あり",$L10>=20,$O10="あり",$N10<>"昼間部の学生",OR('⓪ 事業所設定'!$C$17>=DATE(2026,10,1),($S10+$T10-N($AW10))>=88000)),"加入（短時間労働者）","加入対象外")))) | Y10: =IF($B10="","",TRIM(IF(AND($F10<>"",$F10>=70,ISNUMBER(SEARCH("加入（",$X10))),"厚年対象外（70歳以上被用者該当届） ","")&IF(AND($F10<>"",$F10>=75),"健保対象外（後期高齢者医療） ","")&IF(AND($F10<>"",$F10>=65,$Z10="加入"),"雇保：高年齢被保険者 ",""))) | Z10: =IF($B10="","",IF($H10="役員","対象外（兼務役員なら要相談）",IF(AND($L10>=20,$P10="あり",$N10<>"昼間部の学生"),"加入","加入対象外"))) | AT10: =IF($B10="","",IF($B10="",1,0)+IF($C10="",1,0)+IF($D10="",1,0)+IF($E10="",1,0)+IF($G10="",1,0)+IF($H10="",1,0)+IF($I10="",1,0)+IF($L10="",1,0)+IF($M10="",1,0)+IF($N10="",1,0)+IF($Q10="",1,0)+IF($S10="",1,0)+IF($AA10="",1,0)+IF($AC10="",1,0)+IF($AG10="",1,0)+IF($AH10="",1,0)+IF($AI10="",1,0)+IF($AL10="",1,0)+IF($AP10="",1,0)+IF($AQ10="",1,0)+IF(AND($I10="あり",$J10=""),1,0)+IF(AND($I10="あり",$K10=""),1,0)+IF(AND($AA10="",$AB10=""),1,0)+IF(AND($AC10="あり",$AD10=""),1,0)+IF(AND($AC10="あり",OR($AD10="",$AD10="後日提出"),$AE10=""),1,0)+IF($AV10="",1,0)+IF(AND($AL10="外国",$AM10=""),1,0)+IF(AND($AL10="外国",$AN10=""),1,0)+IF(AND($AL10="外国",$AO10=""),1,0)) | AU10: =IF($B10="","",IF(AND($AA10<>"",$AA10<>"後日提出",$AA10<>"別経路提出",LEN($AA10)<>12),1,0)+IF(AND($AB10<>"",$AB10<>"後日提出",LEN($AB10)<>10),1,0)+IF(AND($AD10<>"",$AD10<>"後日提出",LEN($AD10)<>11),1,0)+IF(AND($AG10<>"",LEN(SUBSTITUTE($AG10,"-",""))<>7),1,0))
A11: =IF($B11="","",ROW()-8) | F11: =IF(OR($E11="",$E11>80000),"",DATEDIF($E11,IF(OR($G11="",$G11>80000),TODAY(),$G11),"Y")) | O11: =IF($B11="","",IF($I11="なし","あり",IF($I11<>"あり","",IF($K11="更新の可能性あり","あり",IF(OR($J11="",$G11=""),"なし",IF(OR(NOT(ISNUMBER($G11)),NOT(ISNUMBER($J11)),$G11>80000,$J11>80000),"要確認（日付）",IF($J11>IF(DAY(EDATE($G11,2))<DAY($G11),EOMONTH($G11,2),EDATE($G11,2)-1),"あり","なし")))))) | P11: =IF($B11="","",IF($I11="なし","あり",IF($I11="あり",IF(OR($K11="更新の可能性あり",AND($J11<>"",$G11<>"",$J11-$G11+1>=31)),"あり","なし"),""))) | W11: =IF($B11="","",SUM($S11,$T11,$U11,$V11)) | X11: =IF(OR('⓪ 事業所設定'!$C$9="",'⓪ 事業所設定'!$C$13="",'⓪ 事業所設定'!$C$14="",'⓪ 事業所設定'!$C$17=""),"事業所設定が未入力です",IF($B11="","",IF(AND($L11>='⓪ 事業所設定'!$C$13*0.75,$M11>='⓪ 事業所設定'!$C$14*0.75,$O11="あり"),"加入（一般被保険者）",IF(AND('⓪ 事業所設定'!$C$12="適用あり",$L11>=20,$O11="あり",$N11<>"昼間部の学生",OR('⓪ 事業所設定'!$C$17>=DATE(2026,10,1),($S11+$T11-N($AW11))>=88000)),"加入（短時間労働者）","加入対象外")))) | Y11: =IF($B11="","",TRIM(IF(AND($F11<>"",$F11>=70,ISNUMBER(SEARCH("加入（",$X11))),"厚年対象外（70歳以上被用者該当届） ","")&IF(AND($F11<>"",$F11>=75),"健保対象外（後期高齢者医療） ","")&IF(AND($F11<>"",$F11>=65,$Z11="加入"),"雇保：高年齢被保険者 ",""))) | Z11: =IF($B11="","",IF($H11="役員","対象外（兼務役員なら要相談）",IF(AND($L11>=20,$P11="あり",$N11<>"昼間部の学生"),"加入","加入対象外"))) | AT11: =IF($B11="","",IF($B11="",1,0)+IF($C11="",1,0)+IF($D11="",1,0)+IF($E11="",1,0)+IF($G11="",1,0)+IF($H11="",1,0)+IF($I11="",1,0)+IF($L11="",1,0)+IF($M11="",1,0)+IF($N11="",1,0)+IF($Q11="",1,0)+IF($S11="",1,0)+IF($AA11="",1,0)+IF($AC11="",1,0)+IF($AG11="",1,0)+IF($AH11="",1,0)+IF($AI11="",1,0)+IF($AL11="",1,0)+IF($AP11="",1,0)+IF($AQ11="",1,0)+IF(AND($I11="あり",$J11=""),1,0)+IF(AND($I11="あり",$K11=""),1,0)+IF(AND($AA11="",$AB11=""),1,0)+IF(AND($AC11="あり",$AD11=""),1,0)+IF(AND($AC11="あり",OR($AD11="",$AD11="後日提出"),$AE11=""),1,0)+IF($AV11="",1,0)+IF(AND($AL11="外国",$AM11=""),1,0)+IF(AND($AL11="外国",$AN11=""),1,0)+IF(AND($AL11="外国",$AO11=""),1,0)) | AU11: =IF($B11="","",IF(AND($AA11<>"",$AA11<>"後日提出",$AA11<>"別経路提出",LEN($AA11)<>12),1,0)+IF(AND($AB11<>"",$AB11<>"後日提出",LEN($AB11)<>10),1,0)+IF(AND($AD11<>"",$AD11<>"後日提出",LEN($AD11)<>11),1,0)+IF(AND($AG11<>"",LEN(SUBSTITUTE($AG11,"-",""))<>7),1,0))
A12: =IF($B12="","",ROW()-8) | F12: =IF(OR($E12="",$E12>80000),"",DATEDIF($E12,IF(OR($G12="",$G12>80000),TODAY(),$G12),"Y")) | O12: =IF($B12="","",IF($I12="なし","あり",IF($I12<>"あり","",IF($K12="更新の可能性あり","あり",IF(OR($J12="",$G12=""),"なし",IF(OR(NOT(ISNUMBER($G12)),NOT(ISNUMBER($J12)),$G12>80000,$J12>80000),"要確認（日付）",IF($J12>IF(DAY(EDATE($G12,2))<DAY($G12),EOMONTH($G12,2),EDATE($G12,2)-1),"あり","なし")))))) | P12: =IF($B12="","",IF($I12="なし","あり",IF($I12="あり",IF(OR($K12="更新の可能性あり",AND($J12<>"",$G12<>"",$J12-$G12+1>=31)),"あり","なし"),""))) | W12: =IF($B12="","",SUM($S12,$T12,$U12,$V12)) | X12: =IF(OR('⓪ 事業所設定'!$C$9="",'⓪ 事業所設定'!$C$13="",'⓪ 事業所設定'!$C$14="",'⓪ 事業所設定'!$C$17=""),"事業所設定が未入力です",IF($B12="","",IF(AND($L12>='⓪ 事業所設定'!$C$13*0.75,$M12>='⓪ 事業所設定'!$C$14*0.75,$O12="あり"),"加入（一般被保険者）",IF(AND('⓪ 事業所設定'!$C$12="適用あり",$L12>=20,$O12="あり",$N12<>"昼間部の学生",OR('⓪ 事業所設定'!$C$17>=DATE(2026,10,1),($S12+$T12-N($AW12))>=88000)),"加入（短時間労働者）","加入対象外")))) | Y12: =IF($B12="","",TRIM(IF(AND($F12<>"",$F12>=70,ISNUMBER(SEARCH("加入（",$X12))),"厚年対象外（70歳以上被用者該当届） ","")&IF(AND($F12<>"",$F12>=75),"健保対象外（後期高齢者医療） ","")&IF(AND($F12<>"",$F12>=65,$Z12="加入"),"雇保：高年齢被保険者 ",""))) | Z12: =IF($B12="","",IF($H12="役員","対象外（兼務役員なら要相談）",IF(AND($L12>=20,$P12="あり",$N12<>"昼間部の学生"),"加入","加入対象外"))) | AT12: =IF($B12="","",IF($B12="",1,0)+IF($C12="",1,0)+IF($D12="",1,0)+IF($E12="",1,0)+IF($G12="",1,0)+IF($H12="",1,0)+IF($I12="",1,0)+IF($L12="",1,0)+IF($M12="",1,0)+IF($N12="",1,0)+IF($Q12="",1,0)+IF($S12="",1,0)+IF($AA12="",1,0)+IF($AC12="",1,0)+IF($AG12="",1,0)+IF($AH12="",1,0)+IF($AI12="",1,0)+IF($AL12="",1,0)+IF($AP12="",1,0)+IF($AQ12="",1,0)+IF(AND($I12="あり",$J12=""),1,0)+IF(AND($I12="あり",$K12=""),1,0)+IF(AND($AA12="",$AB12=""),1,0)+IF(AND($AC12="あり",$AD12=""),1,0)+IF(AND($AC12="あり",OR($AD12="",$AD12="後日提出"),$AE12=""),1,0)+IF($AV12="",1,0)+IF(AND($AL12="外国",$AM12=""),1,0)+IF(AND($AL12="外国",$AN12=""),1,0)+IF(AND($AL12="外国",$AO12=""),1,0)) | AU12: =IF($B12="","",IF(AND($AA12<>"",$AA12<>"後日提出",$AA12<>"別経路提出",LEN($AA12)<>12),1,0)+IF(AND($AB12<>"",$AB12<>"後日提出",LEN($AB12)<>10),1,0)+IF(AND($AD12<>"",$AD12<>"後日提出",LEN($AD12)<>11),1,0)+IF(AND($AG12<>"",LEN(SUBSTITUTE($AG12,"-",""))<>7),1,0))
A13: =IF($B13="","",ROW()-8) | F13: =IF(OR($E13="",$E13>80000),"",DATEDIF($E13,IF(OR($G13="",$G13>80000),TODAY(),$G13),"Y")) | O13: =IF($B13="","",IF($I13="なし","あり",IF($I13<>"あり","",IF($K13="更新の可能性あり","あり",IF(OR($J13="",$G13=""),"なし",IF(OR(NOT(ISNUMBER($G13)),NOT(ISNUMBER($J13)),$G13>80000,$J13>80000),"要確認（日付）",IF($J13>IF(DAY(EDATE($G13,2))<DAY($G13),EOMONTH($G13,2),EDATE($G13,2)-1),"あり","なし")))))) | P13: =IF($B13="","",IF($I13="なし","あり",IF($I13="あり",IF(OR($K13="更新の可能性あり",AND($J13<>"",$G13<>"",$J13-$G13+1>=31)),"あり","なし"),""))) | W13: =IF($B13="","",SUM($S13,$T13,$U13,$V13)) | X13: =IF(OR('⓪ 事業所設定'!$C$9="",'⓪ 事業所設定'!$C$13="",'⓪ 事業所設定'!$C$14="",'⓪ 事業所設定'!$C$17=""),"事業所設定が未入力です",IF($B13="","",IF(AND($L13>='⓪ 事業所設定'!$C$13*0.75,$M13>='⓪ 事業所設定'!$C$14*0.75,$O13="あり"),"加入（一般被保険者）",IF(AND('⓪ 事業所設定'!$C$12="適用あり",$L13>=20,$O13="あり",$N13<>"昼間部の学生",OR('⓪ 事業所設定'!$C$17>=DATE(2026,10,1),($S13+$T13-N($AW13))>=88000)),"加入（短時間労働者）","加入対象外")))) | Y13: =IF($B13="","",TRIM(IF(AND($F13<>"",$F13>=70,ISNUMBER(SEARCH("加入（",$X13))),"厚年対象外（70歳以上被用者該当届） ","")&IF(AND($F13<>"",$F13>=75),"健保対象外（後期高齢者医療） ","")&IF(AND($F13<>"",$F13>=65,$Z13="加入"),"雇保：高年齢被保険者 ",""))) | Z13: =IF($B13="","",IF($H13="役員","対象外（兼務役員なら要相談）",IF(AND($L13>=20,$P13="あり",$N13<>"昼間部の学生"),"加入","加入対象外"))) | AT13: =IF($B13="","",IF($B13="",1,0)+IF($C13="",1,0)+IF($D13="",1,0)+IF($E13="",1,0)+IF($G13="",1,0)+IF($H13="",1,0)+IF($I13="",1,0)+IF($L13="",1,0)+IF($M13="",1,0)+IF($N13="",1,0)+IF($Q13="",1,0)+IF($S13="",1,0)+IF($AA13="",1,0)+IF($AC13="",1,0)+IF($AG13="",1,0)+IF($AH13="",1,0)+IF($AI13="",1,0)+IF($AL13="",1,0)+IF($AP13="",1,0)+IF($AQ13="",1,0)+IF(AND($I13="あり",$J13=""),1,0)+IF(AND($I13="あり",$K13=""),1,0)+IF(AND($AA13="",$AB13=""),1,0)+IF(AND($AC13="あり",$AD13=""),1,0)+IF(AND($AC13="あり",OR($AD13="",$AD13="後日提出"),$AE13=""),1,0)+IF($AV13="",1,0)+IF(AND($AL13="外国",$AM13=""),1,0)+IF(AND($AL13="外国",$AN13=""),1,0)+IF(AND($AL13="外国",$AO13=""),1,0)) | AU13: =IF($B13="","",IF(AND($AA13<>"",$AA13<>"後日提出",$AA13<>"別経路提出",LEN($AA13)<>12),1,0)+IF(AND($AB13<>"",$AB13<>"後日提出",LEN($AB13)<>10),1,0)+IF(AND($AD13<>"",$AD13<>"後日提出",LEN($AD13)<>11),1,0)+IF(AND($AG13<>"",LEN(SUBSTITUTE($AG13,"-",""))<>7),1,0))
A14: =IF($B14="","",ROW()-8) | F14: =IF(OR($E14="",$E14>80000),"",DATEDIF($E14,IF(OR($G14="",$G14>80000),TODAY(),$G14),"Y")) | O14: =IF($B14="","",IF($I14="なし","あり",IF($I14<>"あり","",IF($K14="更新の可能性あり","あり",IF(OR($J14="",$G14=""),"なし",IF(OR(NOT(ISNUMBER($G14)),NOT(ISNUMBER($J14)),$G14>80000,$J14>80000),"要確認（日付）",IF($J14>IF(DAY(EDATE($G14,2))<DAY($G14),EOMONTH($G14,2),EDATE($G14,2)-1),"あり","なし")))))) | P14: =IF($B14="","",IF($I14="なし","あり",IF($I14="あり",IF(OR($K14="更新の可能性あり",AND($J14<>"",$G14<>"",$J14-$G14+1>=31)),"あり","なし"),""))) | W14: =IF($B14="","",SUM($S14,$T14,$U14,$V14)) | X14: =IF(OR('⓪ 事業所設定'!$C$9="",'⓪ 事業所設定'!$C$13="",'⓪ 事業所設定'!$C$14="",'⓪ 事業所設定'!$C$17=""),"事業所設定が未入力です",IF($B14="","",IF(AND($L14>='⓪ 事業所設定'!$C$13*0.75,$M14>='⓪ 事業所設定'!$C$14*0.75,$O14="あり"),"加入（一般被保険者）",IF(AND('⓪ 事業所設定'!$C$12="適用あり",$L14>=20,$O14="あり",$N14<>"昼間部の学生",OR('⓪ 事業所設定'!$C$17>=DATE(2026,10,1),($S14+$T14-N($AW14))>=88000)),"加入（短時間労働者）","加入対象外")))) | Y14: =IF($B14="","",TRIM(IF(AND($F14<>"",$F14>=70,ISNUMBER(SEARCH("加入（",$X14))),"厚年対象外（70歳以上被用者該当届） ","")&IF(AND($F14<>"",$F14>=75),"健保対象外（後期高齢者医療） ","")&IF(AND($F14<>"",$F14>=65,$Z14="加入"),"雇保：高年齢被保険者 ",""))) | Z14: =IF($B14="","",IF($H14="役員","対象外（兼務役員なら要相談）",IF(AND($L14>=20,$P14="あり",$N14<>"昼間部の学生"),"加入","加入対象外"))) | AT14: =IF($B14="","",IF($B14="",1,0)+IF($C14="",1,0)+IF($D14="",1,0)+IF($E14="",1,0)+IF($G14="",1,0)+IF($H14="",1,0)+IF($I14="",1,0)+IF($L14="",1,0)+IF($M14="",1,0)+IF($N14="",1,0)+IF($Q14="",1,0)+IF($S14="",1,0)+IF($AA14="",1,0)+IF($AC14="",1,0)+IF($AG14="",1,0)+IF($AH14="",1,0)+IF($AI14="",1,0)+IF($AL14="",1,0)+IF($AP14="",1,0)+IF($AQ14="",1,0)+IF(AND($I14="あり",$J14=""),1,0)+IF(AND($I14="あり",$K14=""),1,0)+IF(AND($AA14="",$AB14=""),1,0)+IF(AND($AC14="あり",$AD14=""),1,0)+IF(AND($AC14="あり",OR($AD14="",$AD14="後日提出"),$AE14=""),1,0)+IF($AV14="",1,0)+IF(AND($AL14="外国",$AM14=""),1,0)+IF(AND($AL14="外国",$AN14=""),1,0)+IF(AND($AL14="外国",$AO14=""),1,0)) | AU14: =IF($B14="","",IF(AND($AA14<>"",$AA14<>"後日提出",$AA14<>"別経路提出",LEN($AA14)<>12),1,0)+IF(AND($AB14<>"",$AB14<>"後日提出",LEN($AB14)<>10),1,0)+IF(AND($AD14<>"",$AD14<>"後日提出",LEN($AD14)<>11),1,0)+IF(AND($AG14<>"",LEN(SUBSTITUTE($AG14,"-",""))<>7),1,0))
A15: =IF($B15="","",ROW()-8) | F15: =IF(OR($E15="",$E15>80000),"",DATEDIF($E15,IF(OR($G15="",$G15>80000),TODAY(),$G15),"Y")) | O15: =IF($B15="","",IF($I15="なし","あり",IF($I15<>"あり","",IF($K15="更新の可能性あり","あり",IF(OR($J15="",$G15=""),"なし",IF(OR(NOT(ISNUMBER($G15)),NOT(ISNUMBER($J15)),$G15>80000,$J15>80000),"要確認（日付）",IF($J15>IF(DAY(EDATE($G15,2))<DAY($G15),EOMONTH($G15,2),EDATE($G15,2)-1),"あり","なし")))))) | P15: =IF($B15="","",IF($I15="なし","あり",IF($I15="あり",IF(OR($K15="更新の可能性あり",AND($J15<>"",$G15<>"",$J15-$G15+1>=31)),"あり","なし"),""))) | W15: =IF($B15="","",SUM($S15,$T15,$U15,$V15)) | X15: =IF(OR('⓪ 事業所設定'!$C$9="",'⓪ 事業所設定'!$C$13="",'⓪ 事業所設定'!$C$14="",'⓪ 事業所設定'!$C$17=""),"事業所設定が未入力です",IF($B15="","",IF(AND($L15>='⓪ 事業所設定'!$C$13*0.75,$M15>='⓪ 事業所設定'!$C$14*0.75,$O15="あり"),"加入（一般被保険者）",IF(AND('⓪ 事業所設定'!$C$12="適用あり",$L15>=20,$O15="あり",$N15<>"昼間部の学生",OR('⓪ 事業所設定'!$C$17>=DATE(2026,10,1),($S15+$T15-N($AW15))>=88000)),"加入（短時間労働者）","加入対象外")))) | Y15: =IF($B15="","",TRIM(IF(AND($F15<>"",$F15>=70,ISNUMBER(SEARCH("加入（",$X15))),"厚年対象外（70歳以上被用者該当届） ","")&IF(AND($F15<>"",$F15>=75),"健保対象外（後期高齢者医療） ","")&IF(AND($F15<>"",$F15>=65,$Z15="加入"),"雇保：高年齢被保険者 ",""))) | Z15: =IF($B15="","",IF($H15="役員","対象外（兼務役員なら要相談）",IF(AND($L15>=20,$P15="あり",$N15<>"昼間部の学生"),"加入","加入対象外"))) | AT15: =IF($B15="","",IF($B15="",1,0)+IF($C15="",1,0)+IF($D15="",1,0)+IF($E15="",1,0)+IF($G15="",1,0)+IF($H15="",1,0)+IF($I15="",1,0)+IF($L15="",1,0)+IF($M15="",1,0)+IF($N15="",1,0)+IF($Q15="",1,0)+IF($S15="",1,0)+IF($AA15="",1,0)+IF($AC15="",1,0)+IF($AG15="",1,0)+IF($AH15="",1,0)+IF($AI15="",1,0)+IF($AL15="",1,0)+IF($AP15="",1,0)+IF($AQ15="",1,0)+IF(AND($I15="あり",$J15=""),1,0)+IF(AND($I15="あり",$K15=""),1,0)+IF(AND($AA15="",$AB15=""),1,0)+IF(AND($AC15="あり",$AD15=""),1,0)+IF(AND($AC15="あり",OR($AD15="",$AD15="後日提出"),$AE15=""),1,0)+IF($AV15="",1,0)+IF(AND($AL15="外国",$AM15=""),1,0)+IF(AND($AL15="外国",$AN15=""),1,0)+IF(AND($AL15="外国",$AO15=""),1,0)) | AU15: =IF($B15="","",IF(AND($AA15<>"",$AA15<>"後日提出",$AA15<>"別経路提出",LEN($AA15)<>12),1,0)+IF(AND($AB15<>"",$AB15<>"後日提出",LEN($AB15)<>10),1,0)+IF(AND($AD15<>"",$AD15<>"後日提出",LEN($AD15)<>11),1,0)+IF(AND($AG15<>"",LEN(SUBSTITUTE($AG15,"-",""))<>7),1,0))
A16: =IF($B16="","",ROW()-8) | F16: =IF(OR($E16="",$E16>80000),"",DATEDIF($E16,IF(OR($G16="",$G16>80000),TODAY(),$G16),"Y")) | O16: =IF($B16="","",IF($I16="なし","あり",IF($I16<>"あり","",IF($K16="更新の可能性あり","あり",IF(OR($J16="",$G16=""),"なし",IF(OR(NOT(ISNUMBER($G16)),NOT(ISNUMBER($J16)),$G16>80000,$J16>80000),"要確認（日付）",IF($J16>IF(DAY(EDATE($G16,2))<DAY($G16),EOMONTH($G16,2),EDATE($G16,2)-1),"あり","なし")))))) | P16: =IF($B16="","",IF($I16="なし","あり",IF($I16="あり",IF(OR($K16="更新の可能性あり",AND($J16<>"",$G16<>"",$J16-$G16+1>=31)),"あり","なし"),""))) | W16: =IF($B16="","",SUM($S16,$T16,$U16,$V16)) | X16: =IF(OR('⓪ 事業所設定'!$C$9="",'⓪ 事業所設定'!$C$13="",'⓪ 事業所設定'!$C$14="",'⓪ 事業所設定'!$C$17=""),"事業所設定が未入力です",IF($B16="","",IF(AND($L16>='⓪ 事業所設定'!$C$13*0.75,$M16>='⓪ 事業所設定'!$C$14*0.75,$O16="あり"),"加入（一般被保険者）",IF(AND('⓪ 事業所設定'!$C$12="適用あり",$L16>=20,$O16="あり",$N16<>"昼間部の学生",OR('⓪ 事業所設定'!$C$17>=DATE(2026,10,1),($S16+$T16-N($AW16))>=88000)),"加入（短時間労働者）","加入対象外")))) | Y16: =IF($B16="","",TRIM(IF(AND($F16<>"",$F16>=70,ISNUMBER(SEARCH("加入（",$X16))),"厚年対象外（70歳以上被用者該当届） ","")&IF(AND($F16<>"",$F16>=75),"健保対象外（後期高齢者医療） ","")&IF(AND($F16<>"",$F16>=65,$Z16="加入"),"雇保：高年齢被保険者 ",""))) | Z16: =IF($B16="","",IF($H16="役員","対象外（兼務役員なら要相談）",IF(AND($L16>=20,$P16="あり",$N16<>"昼間部の学生"),"加入","加入対象外"))) | AT16: =IF($B16="","",IF($B16="",1,0)+IF($C16="",1,0)+IF($D16="",1,0)+IF($E16="",1,0)+IF($G16="",1,0)+IF($H16="",1,0)+IF($I16="",1,0)+IF($L16="",1,0)+IF($M16="",1,0)+IF($N16="",1,0)+IF($Q16="",1,0)+IF($S16="",1,0)+IF($AA16="",1,0)+IF($AC16="",1,0)+IF($AG16="",1,0)+IF($AH16="",1,0)+IF($AI16="",1,0)+IF($AL16="",1,0)+IF($AP16="",1,0)+IF($AQ16="",1,0)+IF(AND($I16="あり",$J16=""),1,0)+IF(AND($I16="あり",$K16=""),1,0)+IF(AND($AA16="",$AB16=""),1,0)+IF(AND($AC16="あり",$AD16=""),1,0)+IF(AND($AC16="あり",OR($AD16="",$AD16="後日提出"),$AE16=""),1,0)+IF($AV16="",1,0)+IF(AND($AL16="外国",$AM16=""),1,0)+IF(AND($AL16="外国",$AN16=""),1,0)+IF(AND($AL16="外国",$AO16=""),1,0)) | AU16: =IF($B16="","",IF(AND($AA16<>"",$AA16<>"後日提出",$AA16<>"別経路提出",LEN($AA16)<>12),1,0)+IF(AND($AB16<>"",$AB16<>"後日提出",LEN($AB16)<>10),1,0)+IF(AND($AD16<>"",$AD16<>"後日提出",LEN($AD16)<>11),1,0)+IF(AND($AG16<>"",LEN(SUBSTITUTE($AG16,"-",""))<>7),1,0))
A17: =IF($B17="","",ROW()-8) | F17: =IF(OR($E17="",$E17>80000),"",DATEDIF($E17,IF(OR($G17="",$G17>80000),TODAY(),$G17),"Y")) | O17: =IF($B17="","",IF($I17="なし","あり",IF($I17<>"あり","",IF($K17="更新の可能性あり","あり",IF(OR($J17="",$G17=""),"なし",IF(OR(NOT(ISNUMBER($G17)),NOT(ISNUMBER($J17)),$G17>80000,$J17>80000),"要確認（日付）",IF($J17>IF(DAY(EDATE($G17,2))<DAY($G17),EOMONTH($G17,2),EDATE($G17,2)-1),"あり","なし")))))) | P17: =IF($B17="","",IF($I17="なし","あり",IF($I17="あり",IF(OR($K17="更新の可能性あり",AND($J17<>"",$G17<>"",$J17-$G17+1>=31)),"あり","なし"),""))) | W17: =IF($B17="","",SUM($S17,$T17,$U17,$V17)) | X17: =IF(OR('⓪ 事業所設定'!$C$9="",'⓪ 事業所設定'!$C$13="",'⓪ 事業所設定'!$C$14="",'⓪ 事業所設定'!$C$17=""),"事業所設定が未入力です",IF($B17="","",IF(AND($L17>='⓪ 事業所設定'!$C$13*0.75,$M17>='⓪ 事業所設定'!$C$14*0.75,$O17="あり"),"加入（一般被保険者）",IF(AND('⓪ 事業所設定'!$C$12="適用あり",$L17>=20,$O17="あり",$N17<>"昼間部の学生",OR('⓪ 事業所設定'!$C$17>=DATE(2026,10,1),($S17+$T17-N($AW17))>=88000)),"加入（短時間労働者）","加入対象外")))) | Y17: =IF($B17="","",TRIM(IF(AND($F17<>"",$F17>=70,ISNUMBER(SEARCH("加入（",$X17))),"厚年対象外（70歳以上被用者該当届） ","")&IF(AND($F17<>"",$F17>=75),"健保対象外（後期高齢者医療） ","")&IF(AND($F17<>"",$F17>=65,$Z17="加入"),"雇保：高年齢被保険者 ",""))) | Z17: =IF($B17="","",IF($H17="役員","対象外（兼務役員なら要相談）",IF(AND($L17>=20,$P17="あり",$N17<>"昼間部の学生"),"加入","加入対象外"))) | AT17: =IF($B17="","",IF($B17="",1,0)+IF($C17="",1,0)+IF($D17="",1,0)+IF($E17="",1,0)+IF($G17="",1,0)+IF($H17="",1,0)+IF($I17="",1,0)+IF($L17="",1,0)+IF($M17="",1,0)+IF($N17="",1,0)+IF($Q17="",1,0)+IF($S17="",1,0)+IF($AA17="",1,0)+IF($AC17="",1,0)+IF($AG17="",1,0)+IF($AH17="",1,0)+IF($AI17="",1,0)+IF($AL17="",1,0)+IF($AP17="",1,0)+IF($AQ17="",1,0)+IF(AND($I17="あり",$J17=""),1,0)+IF(AND($I17="あり",$K17=""),1,0)+IF(AND($AA17="",$AB17=""),1,0)+IF(AND($AC17="あり",$AD17=""),1,0)+IF(AND($AC17="あり",OR($AD17="",$AD17="後日提出"),$AE17=""),1,0)+IF($AV17="",1,0)+IF(AND($AL17="外国",$AM17=""),1,0)+IF(AND($AL17="外国",$AN17=""),1,0)+IF(AND($AL17="外国",$AO17=""),1,0)) | AU17: =IF($B17="","",IF(AND($AA17<>"",$AA17<>"後日提出",$AA17<>"別経路提出",LEN($AA17)<>12),1,0)+IF(AND($AB17<>"",$AB17<>"後日提出",LEN($AB17)<>10),1,0)+IF(AND($AD17<>"",$AD17<>"後日提出",LEN($AD17)<>11),1,0)+IF(AND($AG17<>"",LEN(SUBSTITUTE($AG17,"-",""))<>7),1,0))
A18: =IF($B18="","",ROW()-8) | F18: =IF(OR($E18="",$E18>80000),"",DATEDIF($E18,IF(OR($G18="",$G18>80000),TODAY(),$G18),"Y")) | O18: =IF($B18="","",IF($I18="なし","あり",IF($I18<>"あり","",IF($K18="更新の可能性あり","あり",IF(OR($J18="",$G18=""),"なし",IF(OR(NOT(ISNUMBER($G18)),NOT(ISNUMBER($J18)),$G18>80000,$J18>80000),"要確認（日付）",IF($J18>IF(DAY(EDATE($G18,2))<DAY($G18),EOMONTH($G18,2),EDATE($G18,2)-1),"あり","なし")))))) | P18: =IF($B18="","",IF($I18="なし","あり",IF($I18="あり",IF(OR($K18="更新の可能性あり",AND($J18<>"",$G18<>"",$J18-$G18+1>=31)),"あり","なし"),""))) | W18: =IF($B18="","",SUM($S18,$T18,$U18,$V18)) | X18: =IF(OR('⓪ 事業所設定'!$C$9="",'⓪ 事業所設定'!$C$13="",'⓪ 事業所設定'!$C$14="",'⓪ 事業所設定'!$C$17=""),"事業所設定が未入力です",IF($B18="","",IF(AND($L18>='⓪ 事業所設定'!$C$13*0.75,$M18>='⓪ 事業所設定'!$C$14*0.75,$O18="あり"),"加入（一般被保険者）",IF(AND('⓪ 事業所設定'!$C$12="適用あり",$L18>=20,$O18="あり",$N18<>"昼間部の学生",OR('⓪ 事業所設定'!$C$17>=DATE(2026,10,1),($S18+$T18-N($AW18))>=88000)),"加入（短時間労働者）","加入対象外")))) | Y18: =IF($B18="","",TRIM(IF(AND($F18<>"",$F18>=70,ISNUMBER(SEARCH("加入（",$X18))),"厚年対象外（70歳以上被用者該当届） ","")&IF(AND($F18<>"",$F18>=75),"健保対象外（後期高齢者医療） ","")&IF(AND($F18<>"",$F18>=65,$Z18="加入"),"雇保：高年齢被保険者 ",""))) | Z18: =IF($B18="","",IF($H18="役員","対象外（兼務役員なら要相談）",IF(AND($L18>=20,$P18="あり",$N18<>"昼間部の学生"),"加入","加入対象外"))) | AT18: =IF($B18="","",IF($B18="",1,0)+IF($C18="",1,0)+IF($D18="",1,0)+IF($E18="",1,0)+IF($G18="",1,0)+IF($H18="",1,0)+IF($I18="",1,0)+IF($L18="",1,0)+IF($M18="",1,0)+IF($N18="",1,0)+IF($Q18="",1,0)+IF($S18="",1,0)+IF($AA18="",1,0)+IF($AC18="",1,0)+IF($AG18="",1,0)+IF($AH18="",1,0)+IF($AI18="",1,0)+IF($AL18="",1,0)+IF($AP18="",1,0)+IF($AQ18="",1,0)+IF(AND($I18="あり",$J18=""),1,0)+IF(AND($I18="あり",$K18=""),1,0)+IF(AND($AA18="",$AB18=""),1,0)+IF(AND($AC18="あり",$AD18=""),1,0)+IF(AND($AC18="あり",OR($AD18="",$AD18="後日提出"),$AE18=""),1,0)+IF($AV18="",1,0)+IF(AND($AL18="外国",$AM18=""),1,0)+IF(AND($AL18="外国",$AN18=""),1,0)+IF(AND($AL18="外国",$AO18=""),1,0)) | AU18: =IF($B18="","",IF(AND($AA18<>"",$AA18<>"後日提出",$AA18<>"別経路提出",LEN($AA18)<>12),1,0)+IF(AND($AB18<>"",$AB18<>"後日提出",LEN($AB18)<>10),1,0)+IF(AND($AD18<>"",$AD18<>"後日提出",LEN($AD18)<>11),1,0)+IF(AND($AG18<>"",LEN(SUBSTITUTE($AG18,"-",""))<>7),1,0))
A19: =IF($B19="","",ROW()-8) | F19: =IF(OR($E19="",$E19>80000),"",DATEDIF($E19,IF(OR($G19="",$G19>80000),TODAY(),$G19),"Y")) | O19: =IF($B19="","",IF($I19="なし","あり",IF($I19<>"あり","",IF($K19="更新の可能性あり","あり",IF(OR($J19="",$G19=""),"なし",IF(OR(NOT(ISNUMBER($G19)),NOT(ISNUMBER($J19)),$G19>80000,$J19>80000),"要確認（日付）",IF($J19>IF(DAY(EDATE($G19,2))<DAY($G19),EOMONTH($G19,2),EDATE($G19,2)-1),"あり","なし")))))) | P19: =IF($B19="","",IF($I19="なし","あり",IF($I19="あり",IF(OR($K19="更新の可能性あり",AND($J19<>"",$G19<>"",$J19-$G19+1>=31)),"あり","なし"),""))) | W19: =IF($B19="","",SUM($S19,$T19,$U19,$V19)) | X19: =IF(OR('⓪ 事業所設定'!$C$9="",'⓪ 事業所設定'!$C$13="",'⓪ 事業所設定'!$C$14="",'⓪ 事業所設定'!$C$17=""),"事業所設定が未入力です",IF($B19="","",IF(AND($L19>='⓪ 事業所設定'!$C$13*0.75,$M19>='⓪ 事業所設定'!$C$14*0.75,$O19="あり"),"加入（一般被保険者）",IF(AND('⓪ 事業所設定'!$C$12="適用あり",$L19>=20,$O19="あり",$N19<>"昼間部の学生",OR('⓪ 事業所設定'!$C$17>=DATE(2026,10,1),($S19+$T19-N($AW19))>=88000)),"加入（短時間労働者）","加入対象外")))) | Y19: =IF($B19="","",TRIM(IF(AND($F19<>"",$F19>=70,ISNUMBER(SEARCH("加入（",$X19))),"厚年対象外（70歳以上被用者該当届） ","")&IF(AND($F19<>"",$F19>=75),"健保対象外（後期高齢者医療） ","")&IF(AND($F19<>"",$F19>=65,$Z19="加入"),"雇保：高年齢被保険者 ",""))) | Z19: =IF($B19="","",IF($H19="役員","対象外（兼務役員なら要相談）",IF(AND($L19>=20,$P19="あり",$N19<>"昼間部の学生"),"加入","加入対象外"))) | AT19: =IF($B19="","",IF($B19="",1,0)+IF($C19="",1,0)+IF($D19="",1,0)+IF($E19="",1,0)+IF($G19="",1,0)+IF($H19="",1,0)+IF($I19="",1,0)+IF($L19="",1,0)+IF($M19="",1,0)+IF($N19="",1,0)+IF($Q19="",1,0)+IF($S19="",1,0)+IF($AA19="",1,0)+IF($AC19="",1,0)+IF($AG19="",1,0)+IF($AH19="",1,0)+IF($AI19="",1,0)+IF($AL19="",1,0)+IF($AP19="",1,0)+IF($AQ19="",1,0)+IF(AND($I19="あり",$J19=""),1,0)+IF(AND($I19="あり",$K19=""),1,0)+IF(AND($AA19="",$AB19=""),1,0)+IF(AND($AC19="あり",$AD19=""),1,0)+IF(AND($AC19="あり",OR($AD19="",$AD19="後日提出"),$AE19=""),1,0)+IF($AV19="",1,0)+IF(AND($AL19="外国",$AM19=""),1,0)+IF(AND($AL19="外国",$AN19=""),1,0)+IF(AND($AL19="外国",$AO19=""),1,0)) | AU19: =IF($B19="","",IF(AND($AA19<>"",$AA19<>"後日提出",$AA19<>"別経路提出",LEN($AA19)<>12),1,0)+IF(AND($AB19<>"",$AB19<>"後日提出",LEN($AB19)<>10),1,0)+IF(AND($AD19<>"",$AD19<>"後日提出",LEN($AD19)<>11),1,0)+IF(AND($AG19<>"",LEN(SUBSTITUTE($AG19,"-",""))<>7),1,0))
A20: =IF($B20="","",ROW()-8) | F20: =IF(OR($E20="",$E20>80000),"",DATEDIF($E20,IF(OR($G20="",$G20>80000),TODAY(),$G20),"Y")) | O20: =IF($B20="","",IF($I20="なし","あり",IF($I20<>"あり","",IF($K20="更新の可能性あり","あり",IF(OR($J20="",$G20=""),"なし",IF(OR(NOT(ISNUMBER($G20)),NOT(ISNUMBER($J20)),$G20>80000,$J20>80000),"要確認（日付）",IF($J20>IF(DAY(EDATE($G20,2))<DAY($G20),EOMONTH($G20,2),EDATE($G20,2)-1),"あり","なし")))))) | P20: =IF($B20="","",IF($I20="なし","あり",IF($I20="あり",IF(OR($K20="更新の可能性あり",AND($J20<>"",$G20<>"",$J20-$G20+1>=31)),"あり","なし"),""))) | W20: =IF($B20="","",SUM($S20,$T20,$U20,$V20)) | X20: =IF(OR('⓪ 事業所設定'!$C$9="",'⓪ 事業所設定'!$C$13="",'⓪ 事業所設定'!$C$14="",'⓪ 事業所設定'!$C$17=""),"事業所設定が未入力です",IF($B20="","",IF(AND($L20>='⓪ 事業所設定'!$C$13*0.75,$M20>='⓪ 事業所設定'!$C$14*0.75,$O20="あり"),"加入（一般被保険者）",IF(AND('⓪ 事業所設定'!$C$12="適用あり",$L20>=20,$O20="あり",$N20<>"昼間部の学生",OR('⓪ 事業所設定'!$C$17>=DATE(2026,10,1),($S20+$T20-N($AW20))>=88000)),"加入（短時間労働者）","加入対象外")))) | Y20: =IF($B20="","",TRIM(IF(AND($F20<>"",$F20>=70,ISNUMBER(SEARCH("加入（",$X20))),"厚年対象外（70歳以上被用者該当届） ","")&IF(AND($F20<>"",$F20>=75),"健保対象外（後期高齢者医療） ","")&IF(AND($F20<>"",$F20>=65,$Z20="加入"),"雇保：高年齢被保険者 ",""))) | Z20: =IF($B20="","",IF($H20="役員","対象外（兼務役員なら要相談）",IF(AND($L20>=20,$P20="あり",$N20<>"昼間部の学生"),"加入","加入対象外"))) | AT20: =IF($B20="","",IF($B20="",1,0)+IF($C20="",1,0)+IF($D20="",1,0)+IF($E20="",1,0)+IF($G20="",1,0)+IF($H20="",1,0)+IF($I20="",1,0)+IF($L20="",1,0)+IF($M20="",1,0)+IF($N20="",1,0)+IF($Q20="",1,0)+IF($S20="",1,0)+IF($AA20="",1,0)+IF($AC20="",1,0)+IF($AG20="",1,0)+IF($AH20="",1,0)+IF($AI20="",1,0)+IF($AL20="",1,0)+IF($AP20="",1,0)+IF($AQ20="",1,0)+IF(AND($I20="あり",$J20=""),1,0)+IF(AND($I20="あり",$K20=""),1,0)+IF(AND($AA20="",$AB20=""),1,0)+IF(AND($AC20="あり",$AD20=""),1,0)+IF(AND($AC20="あり",OR($AD20="",$AD20="後日提出"),$AE20=""),1,0)+IF($AV20="",1,0)+IF(AND($AL20="外国",$AM20=""),1,0)+IF(AND($AL20="外国",$AN20=""),1,0)+IF(AND($AL20="外国",$AO20=""),1,0)) | AU20: =IF($B20="","",IF(AND($AA20<>"",$AA20<>"後日提出",$AA20<>"別経路提出",LEN($AA20)<>12),1,0)+IF(AND($AB20<>"",$AB20<>"後日提出",LEN($AB20)<>10),1,0)+IF(AND($AD20<>"",$AD20<>"後日提出",LEN($AD20)<>11),1,0)+IF(AND($AG20<>"",LEN(SUBSTITUTE($AG20,"-",""))<>7),1,0))
... A58: =IF($B58="","",ROW()-8) | F58: =IF(OR($E58="",$E58>80000),"",DATEDIF($E58,IF(OR($G58="",$G58>80000),TODAY(),$G58),"Y")) | O58: =IF($B58="","",IF($I58="なし","あり",IF($I58<>"あり","",IF($K58="更新の可能性あり","あり",IF(OR($J58="",$G58=""),"なし",IF(OR(NOT(ISNUMBER($G58)),NOT(ISNUMBER($J58)),$G58>80000,$J58>80000),"要確認（日付）",IF($J58>IF(DAY(EDATE($G58,2))<DAY($G58),EOMONTH($G58,2),EDATE($G58,2)-1),"あり","なし")))))) | P58: =IF($B58="","",IF($I58="なし","あり",IF($I58="あり",IF(OR($K58="更新の可能性あり",AND($J58<>"",$G58<>"",$J58-$G58+1>=31)),"あり","なし"),""))) | W58: =IF($B58="","",SUM($S58,$T58,$U58,$V58)) | X58: =IF(OR('⓪ 事業所設定'!$C$9="",'⓪ 事業所設定'!$C$13="",'⓪ 事業所設定'!$C$14="",'⓪ 事業所設定'!$C$17=""),"事業所設定が未入力です",IF($B58="","",IF(AND($L58>='⓪ 事業所設定'!$C$13*0.75,$M58>='⓪ 事業所設定'!$C$14*0.75,$O58="あり"),"加入（一般被保険者）",IF(AND('⓪ 事業所設定'!$C$12="適用あり",$L58>=20,$O58="あり",$N58<>"昼間部の学生",OR('⓪ 事業所設定'!$C$17>=DATE(2026,10,1),($S58+$T58-N($AW58))>=88000)),"加入（短時間労働者）","加入対象外")))) | Y58: =IF($B58="","",TRIM(IF(AND($F58<>"",$F58>=70,ISNUMBER(SEARCH("加入（",$X58))),"厚年対象外（70歳以上被用者該当届） ","")&IF(AND($F58<>"",$F58>=75),"健保対象外（後期高齢者医療） ","")&IF(AND($F58<>"",$F58>=65,$Z58="加入"),"雇保：高年齢被保険者 ",""))) | Z58: =IF($B58="","",IF($H58="役員","対象外（兼務役員なら要相談）",IF(AND($L58>=20,$P58="あり",$N58<>"昼間部の学生"),"加入","加入対象外"))) | AT58: =IF($B58="","",IF($B58="",1,0)+IF($C58="",1,0)+IF($D58="",1,0)+IF($E58="",1,0)+IF($G58="",1,0)+IF($H58="",1,0)+IF($I58="",1,0)+IF($L58="",1,0)+IF($M58="",1,0)+IF($N58="",1,0)+IF($Q58="",1,0)+IF($S58="",1,0)+IF($AA58="",1,0)+IF($AC58="",1,0)+IF($AG58="",1,0)+IF($AH58="",1,0)+IF($AI58="",1,0)+IF($AL58="",1,0)+IF($AP58="",1,0)+IF($AQ58="",1,0)+IF(AND($I58="あり",$J58=""),1,0)+IF(AND($I58="あり",$K58=""),1,0)+IF(AND($AA58="",$AB58=""),1,0)+IF(AND($AC58="あり",$AD58=""),1,0)+IF(AND($AC58="あり",OR($AD58="",$AD58="後日提出"),$AE58=""),1,0)+IF($AV58="",1,0)+IF(AND($AL58="外国",$AM58=""),1,0)+IF(AND($AL58="外国",$AN58=""),1,0)+IF(AND($AL58="外国",$AO58=""),1,0)) | AU58: =IF($B58="","",IF(AND($AA58<>"",$AA58<>"後日提出",$AA58<>"別経路提出",LEN($AA58)<>12),1,0)+IF(AND($AB58<>"",$AB58<>"後日提出",LEN($AB58)<>10),1,0)+IF(AND($AD58<>"",$AD58<>"後日提出",LEN($AD58)<>11),1,0)+IF(AND($AG58<>"",LEN(SUBSTITUTE($AG58,"-",""))<>7),1,0))

Sheet ② 被扶養者情報
A1: ② 被扶養者情報
A3: 入力対象人数 | C3: 必須充足人数 | E3: 必須未入力 残件数 | G3: 完了率
A4: =COUNTA(B8:B67) | C4: =COUNTIF(O8:O67,0) | E4: =SUM(O8:O67) | G4: =IF(A4=0,0,C4/A4)
A5: =IF(A4=0,"（被扶養者がいる場合のみ入力してください）",IF(E4=0,"✓ 必須の未入力はありません","⚠ 必須の未入力が "&E4&" 件あります：本体の赤いセルをご確認ください"))
A6: 対象フォーム内No. 【必】 | B6: 氏名（漢字） 【必】 | C6: フリガナ 【必】 | D6: 続柄 【必】 | E6: 生年月日 【必】 | F6: 性別 【必】 | G6: マイナンバー(12桁) 【必】 | H6: 同居・別居 【必】 | I6: 年間収入見込（円） ※万円ではありません 【必】 | J6: 職業 【任】 | K6: 被扶養者になった日 【必】 | L6: 国民年金 第3号該当 【任】 | M6: 備考 【任】 | P6: ご住所（別居のとき） 【条件必須】別居のとき
A7: 1 | B7: 山田 花子 | C7: ヤマダ ハナコ | D7: 配偶者 | E7: 33826 | F7: 女 | G7: 210987654321 | H7: 同居 | I7: 1030000 | J7: パート勤務 | K7: 46204 | L7: 該当 | M7: ← この行は記入例です。8行目からご記入ください（消しても構いません） | P7: （同居のため記入不要）
O8: =IF($B8="","",IF($A8="",1,0)+IF($B8="",1,0)+IF($C8="",1,0)+IF($D8="",1,0)+IF($E8="",1,0)+IF($F8="",1,0)+IF($G8="",1,0)+IF($H8="",1,0)+IF($I8="",1,0)+IF($K8="",1,0)+IF(AND($H8="別居",$P8=""),1,0))
O9: =IF($B9="","",IF($A9="",1,0)+IF($B9="",1,0)+IF($C9="",1,0)+IF($D9="",1,0)+IF($E9="",1,0)+IF($F9="",1,0)+IF($G9="",1,0)+IF($H9="",1,0)+IF($I9="",1,0)+IF($K9="",1,0)+IF(AND($H9="別居",$P9=""),1,0))
O10: =IF($B10="","",IF($A10="",1,0)+IF($B10="",1,0)+IF($C10="",1,0)+IF($D10="",1,0)+IF($E10="",1,0)+IF($F10="",1,0)+IF($G10="",1,0)+IF($H10="",1,0)+IF($I10="",1,0)+IF($K10="",1,0)+IF(AND($H10="別居",$P10=""),1,0))
O11: =IF($B11="","",IF($A11="",1,0)+IF($B11="",1,0)+IF($C11="",1,0)+IF($D11="",1,0)+IF($E11="",1,0)+IF($F11="",1,0)+IF($G11="",1,0)+IF($H11="",1,0)+IF($I11="",1,0)+IF($K11="",1,0)+IF(AND($H11="別居",$P11=""),1,0))
O12: =IF($B12="","",IF($A12="",1,0)+IF($B12="",1,0)+IF($C12="",1,0)+IF($D12="",1,0)+IF($E12="",1,0)+IF($F12="",1,0)+IF($G12="",1,0)+IF($H12="",1,0)+IF($I12="",1,0)+IF($K12="",1,0)+IF(AND($H12="別居",$P12=""),1,0))
O13: =IF($B13="","",IF($A13="",1,0)+IF($B13="",1,0)+IF($C13="",1,0)+IF($D13="",1,0)+IF($E13="",1,0)+IF($F13="",1,0)+IF($G13="",1,0)+IF($H13="",1,0)+IF($I13="",1,0)+IF($K13="",1,0)+IF(AND($H13="別居",$P13=""),1,0))
O14: =IF($B14="","",IF($A14="",1,0)+IF($B14="",1,0)+IF($C14="",1,0)+IF($D14="",1,0)+IF($E14="",1,0)+IF($F14="",1,0)+IF($G14="",1,0)+IF($H14="",1,0)+IF($I14="",1,0)+IF($K14="",1,0)+IF(AND($H14="別居",$P14=""),1,0))
O15: =IF($B15="","",IF($A15="",1,0)+IF($B15="",1,0)+IF($C15="",1,0)+IF($D15="",1,0)+IF($E15="",1,0)+IF($F15="",1,0)+IF($G15="",1,0)+IF($H15="",1,0)+IF($I15="",1,0)+IF($K15="",1,0)+IF(AND($H15="別居",$P15=""),1,0))
O16: =IF($B16="","",IF($A16="",1,0)+IF($B16="",1,0)+IF($C16="",1,0)+IF($D16="",1,0)+IF($E16="",1,0)+IF($F16="",1,0)+IF($G16="",1,0)+IF($H16="",1,0)+IF($I16="",1,0)+IF($K16="",1,0)+IF(AND($H16="別居",$P16=""),1,0))
O17: =IF($B17="","",IF($A17="",1,0)+IF($B17="",1,0)+IF($C17="",1,0)+IF($D17="",1,0)+IF($E17="",1,0)+IF($F17="",1,0)+IF($G17="",1,0)+IF($H17="",1,0)+IF($I17="",1,0)+IF($K17="",1,0)+IF(AND($H17="別居",$P17=""),1,0))
O18: =IF($B18="","",IF($A18="",1,0)+IF($B18="",1,0)+IF($C18="",1,0)+IF($D18="",1,0)+IF($E18="",1,0)+IF($F18="",1,0)+IF($G18="",1,0)+IF($H18="",1,0)+IF($I18="",1,0)+IF($K18="",1,0)+IF(AND($H18="別居",$P18=""),1,0))
O19: =IF($B19="","",IF($A19="",1,0)+IF($B19="",1,0)+IF($C19="",1,0)+IF($D19="",1,0)+IF($E19="",1,0)+IF($F19="",1,0)+IF($G19="",1,0)+IF($H19="",1,0)+IF($I19="",1,0)+IF($K19="",1,0)+IF(AND($H19="別居",$P19=""),1,0))
... O67: =IF($B67="","",IF($A67="",1,0)+IF($B67="",1,0)+IF($C67="",1,0)+IF($D67="",1,0)+IF($E67="",1,0)+IF($F67="",1,0)+IF($G67="",1,0)+IF($H67="",1,0)+IF($I67="",1,0)+IF($K67="",1,0)+IF(AND($H67="別居",$P67=""),1,0))

Sheet _マスタ（非表示）
A1: 性別 | B1: 雇用形態 | C1: 賃金形態 | D1: 更新見込み | E1: 後日提出 | F1: 番号提出状態 | G1: あり/なし | H1: なし/あり | I1: 学生区分 | J1: 前職雇保 | K1: 健保種類 | L1: 任意申出 | M1: 資格確認書 | N1: 続柄 | O1: 同居・別居 | P1: 第3号 | Q1: 国籍 | R1: 都道府県 | S1: 職種 | T1: 現物給与の種類
A2: 男 | B2: 正社員 | C2: 月給 | D2: 未定 | E2: 後日提出 | F2: 後日提出 | G2: あり | H2: なし | I2: 学生ではない | J2: あり | K2: 協会けんぽ | L2: あり | M2: 要（マイナ保険証 未登録） | N2: 配偶者 | O2: 同居 | P2: 該当 | Q2: 日本 | R2: 北海道 | S2: 専門的・技術的職業 | T2: 社宅・寮
A3: 女 | B3: 契約社員 | C3: 日給 | D3: 更新の可能性あり | F3: 別経路提出 | G3: なし | H3: あり | I3: 夜間・定時制・通信制 | J3: なし | K3: 健康保険組合 | L3: なし | M3: 否（登録済み） | N3: 子 | O3: 別居 | P3: 非該当 | Q3: 外国 | R3: 青森県 | S3: 管理的職業 | T3: 食事
B4: パート | C4: 時給 | D4: 更新しない | I4: 昼間部の学生 | J4: 不明 | M4: 不明 | N4: 父 | R4: 岩手県 | S4: 事務的職業 | T4: 定期券・通勤定期
B5: アルバイト | C5: 年俸 | N5: 母 | R5: 宮城県 | S5: 販売の職業 | T5: 制服以外の被服
B6: 役員 | C6: その他 | N6: 祖父母 | R6: 秋田県 | S6: サービスの職業 | T6: その他
B7: その他 | N7: 兄弟姉妹 | R7: 山形県 | S7: 保安の職業
N8: その他 | R8: 福島県 | S8: 農林漁業の職業
R9: 茨城県 | S9: 生産工程の職業
R10: 栃木県 | S10: 輸送・機械運転の職業
R11: 群馬県 | S11: 建設・採掘の職業
R12: 埼玉県 | S12: 運搬・清掃・包装等の職業
R13: 千葉県 | S13: 分からない
R14: 東京都
R15: 神奈川県
R16: 新潟県
R17: 富山県
R18: 石川県
R19: 福井県
R20: 山梨県
R21: 長野県
R22: 岐阜県
R23: 静岡県
R24: 愛知県
R25: 三重県
... R48: 沖縄県

Sheet _制御（非表示）
A1: データシート | B1: ① 従業員情報（本人）
A2: 開始行 | B2: 9
A3: 終了行 | B3: 58
A4: 見出し行 | B4: 7
A5: B | B5: kanji | C5: 氏名（漢字） | D5: 0
A6: C | B6: kana | C6: 氏名（フリガナ） | D6: 25
A7: E | B7: date | C7: 生年月日 | D7: 0
A8: G | B8: date | C8: 入社日／資格取得日 | D8: 0
A9: J | B9: date | C9: 契約満了日 | D9: 0
A10: AA | B10: num | C10: マイナンバー(12桁) | D10: 0
A11: AB | B11: numh | C11: 基礎年金番号(10桁) | D11: 0
A12: AD | B12: numh | C12: 雇用保険被保険者番号(11桁) | D12: 0
A13: AE | B13: zen | C13: 前職の事業所名(番号不明時) | D13: 0
A14: AF | B14: date | C14: 前職の退職年月日(番号不明時) | D14: 0
A15: AG | B15: numh | C15: 郵便番号 | D15: 0
A16: AI | B16: zen | C16: 市区町村以下 | D16: 0
... A20: AO | B20: latin | C20: ローマ字氏名 | D20: 0

Sheet _制御②（非表示）
A1: データシート | B1: ② 被扶養者情報
A2: 開始行 | B2: 8
A3: 終了行 | B3: 67
A4: 見出し行 | B4: 6
A5: B | B5: kanji | C5: 氏名（漢字） | D5: 0
A6: C | B6: kana | C6: フリガナ | D6: 25
A7: E | B7: date | C7: 生年月日 | D7: 0
A8: G | B8: num | C8: マイナンバー(12桁) | D8: 0
A9: K | B9: date | C9: 被扶養者になった日 | D9: 0
